torchrl_agents/__init__.py
torchrl_agents/ddpg.py
torchrl_agents/dqn.py
torchrl_agents/ppo.py
torchrl_agents/py.typed
torchrl_agents/sac.py
torchrl_agents-0.4.12.dist-info/METADATA
torchrl_agents-0.4.12.dist-info/WHEEL
torchrl_agents-0.4.12.dist-info/licenses/LICENSE
torchrl_agents-0.4.12.dist-info/RECORD
