Metadata-Version: 2.4
Name: torchrl-agents
Version: 0.4.12
Summary: Object-oriented RL agents based on torchrl.
Project-URL: Homepage, https://github.com/valterschutz/torchrl-agents
Author-email: Valter Schutz <valterschutz@proton.me>
License: Copyright © 2025 Valter Schütz
License-File: LICENSE
Classifier: Intended Audience :: Science/Research
Classifier: License :: OSI Approved :: MIT License
Classifier: Programming Language :: Python
Classifier: Programming Language :: Python :: 3
Classifier: Topic :: Scientific/Engineering :: Artificial Intelligence
Requires-Python: >=3.10
Requires-Dist: pyyaml>=6.0.2
Requires-Dist: torchrl>=0.8.0
